axon_networks_beta_v1/__init__.py
axon_networks_beta_v1/centralized_agent.py
axon_networks_beta_v1/mock_causal_ai_model.py
axon_networks_beta_v1/mock_db_connector.py
axon_networks_beta_v1/supply_chain_node.py
axon_networks_beta-0.0.2.dist-info/LICENSE
axon_networks_beta-0.0.2.dist-info/METADATA
axon_networks_beta-0.0.2.dist-info/WHEEL
axon_networks_beta-0.0.2.dist-info/top_level.txt
axon_networks_beta-0.0.2.dist-info/RECORD
