Metadata-Version: 2.1
Name: axon-networks-beta
Version: 0.0.2
Summary: A beta framework for creating digital twin of supply chain networks
Home-page: 
Author: Antony Alappat
Author-email: antony.alappat@gmail.com
Classifier: Programming Language :: Python :: 3
Classifier: License :: OSI Approved :: MIT License
Classifier: Operating System :: OS Independent
Requires-Python: >=3.6
License-File: LICENSE
